trollsift/__init__.py
trollsift/parser.py
trollsift/py.typed
trollsift/version.py
trollsift/tests/__init__.py
trollsift/tests/integrationtests/__init__.py
trollsift/tests/integrationtests/test_parser.py
trollsift/tests/regressiontests/__init__.py
trollsift/tests/regressiontests/test_parser.py
trollsift/tests/unittests/__init__.py
trollsift/tests/unittests/test_parser.py
trollsift-0.6.0.dist-info/METADATA
trollsift-0.6.0.dist-info/WHEEL
trollsift-0.6.0.dist-info/licenses/LICENSE.txt
trollsift-0.6.0.dist-info/RECORD
