Metadata-Version: 2.4
Name: trollsift
Version: 0.6.0
Summary: String parser/formatter
Author-email: The Pytroll Team <pytroll@googlegroups.com>
License-Expression: GPL-3.0-or-later
License-File: LICENSE.txt
Keywords: pytroll,string formatting,string parsing
Classifier: Development Status :: 5 - Production/Stable
Classifier: Intended Audience :: Science/Research
Classifier: Operating System :: OS Independent
Classifier: Programming Language :: Python
Classifier: Topic :: Scientific/Engineering
Classifier: Typing :: Typed
Requires-Python: >=3.9
